{
  "defaultProperty": {
    "publicAddress": "demo.com",
    "ports": {
      "1": 8000
    }
  },
  "nodes": [
    {
      "nodeId": "node0",
      "instances": [
        {
          "type": 1
        },
        {
          "type": 2,
          "publicPort": 8011
        }
      ]
    },
    {
      "nodeId": "cluster1node1rpc",
      "instances": [
        {
          "type": 2,
          "publicPort": 6011
        }
      ]
    },
    {
      "nodeId": "cluster1GateWay",
      "instances": [
        {
          "publicAddress": "demo.com",
          "type": 4
        }
      ]
    }
  ]
}